puckdb/__init__.py
puckdb-0.9.2.dist-info/LICENSE
puckdb-0.9.2.dist-info/METADATA
puckdb-0.9.2.dist-info/WHEEL
puckdb-0.9.2.dist-info/top_level.txt
puckdb-0.9.2.dist-info/RECORD
